ipython_ctrlr_fzf/__init__.py
ipython_ctrlr_fzf/__main__.py
ipython_ctrlr_fzf-0.2.1.dist-info/METADATA
ipython_ctrlr_fzf-0.2.1.dist-info/WHEEL
ipython_ctrlr_fzf-0.2.1.dist-info/RECORD
