Metadata-Version: 2.1
Name: ipython-ctrlr-fzf
Version: 0.2.1
Summary: overrides ipython's backwards search to use fzf
Home-page: https://github.com/iloveitaly/ipython-ctrlr-fzf
License: MIT
Keywords: ipython,fzf,ipython-extension
Author: Mike Bianco
Author-email: mike@mikebian.co
Requires-Python: >=3.10,<4.0
Classifier: License :: OSI Approved :: MIT License
Classifier: Programming Language :: Python :: 3
Classifier: Programming Language :: Python :: 3.10
Classifier: Programming Language :: Python :: 3.11
Classifier: Programming Language :: Python :: 3.12
Requires-Dist: prompt-toolkit (>=3.0.41,<4.0.0)
Requires-Dist: pyfzf (>=0.3.1,<0.4.0)
